spectrans/__init__.py
spectrans/blocks/__init__.py
spectrans/blocks/base.py
spectrans/blocks/hybrid.py
spectrans/blocks/spectral.py
spectrans/config/__init__.py
spectrans/config/builder.py
spectrans/config/core.py
spectrans/config/models.py
spectrans/config/layers/__init__.py
spectrans/config/layers/attention.py
spectrans/config/layers/mixing.py
spectrans/core/__init__.py
spectrans/core/base.py
spectrans/core/registry.py
spectrans/core/types.py
spectrans/kernels/__init__.py
spectrans/kernels/base.py
spectrans/kernels/rff.py
spectrans/kernels/spectral.py
spectrans/layers/__init__.py
spectrans/layers/attention/__init__.py
spectrans/layers/attention/lst.py
spectrans/layers/attention/spectral.py
spectrans/layers/mixing/__init__.py
spectrans/layers/mixing/afno.py
spectrans/layers/mixing/base.py
spectrans/layers/mixing/fourier.py
spectrans/layers/mixing/global_filter.py
spectrans/layers/mixing/wavelet.py
spectrans/layers/operators/__init__.py
spectrans/layers/operators/fno.py
spectrans/models/__init__.py
spectrans/models/afno.py
spectrans/models/base.py
spectrans/models/fnet.py
spectrans/models/fno_transformer.py
spectrans/models/gfnet.py
spectrans/models/hybrid.py
spectrans/models/lst.py
spectrans/models/spectral_attention.py
spectrans/models/wavenet_transformer.py
spectrans/transforms/__init__.py
spectrans/transforms/base.py
spectrans/transforms/cosine.py
spectrans/transforms/fourier.py
spectrans/transforms/hadamard.py
spectrans/transforms/wavelet.py
spectrans/utils/__init__.py
spectrans/utils/complex.py
spectrans/utils/fft.py
spectrans/utils/initialization.py
spectrans/utils/padding.py
spectrans-0.1.0.dist-info/licenses/LICENSE
spectrans-0.1.0.dist-info/METADATA
spectrans-0.1.0.dist-info/WHEEL
spectrans-0.1.0.dist-info/top_level.txt
spectrans-0.1.0.dist-info/RECORD
