Metadata-Version: 2.4
Name: spectrans
Version: 0.1.0
Summary: Modular spectral transformer implementations in PyTorch
Author-email: Aaron Steven White <aaronstevenwhite@gmail.com>
License-Expression: MIT
Project-URL: Repository, https://github.com/aaronstevenwhite/spectrans
Project-URL: Documentation, https://spectrans.readthedocs.io
Keywords: deep-learning,transformers,pytorch,neural-networks,fft,wavelets,spectral-methods,sequence-modeling
Classifier: Development Status :: 3 - Alpha
Classifier: Intended Audience :: Science/Research
Classifier: Programming Language :: Python :: 3.13
Classifier: Topic :: Scientific/Engineering :: Artificial Intelligence
Requires-Python: >=3.13
License-File: LICENSE
Requires-Dist: torch>=2.5.0
Requires-Dist: numpy>=2.0.0
Requires-Dist: scipy>=1.16.1
Requires-Dist: pyyaml>=6.0.2
Requires-Dist: einops>=0.8.0
Requires-Dist: PyWavelets>=1.6.0
Requires-Dist: pydantic>=2.11.0
Provides-Extra: dev
Requires-Dist: pytest>=8.3.0; extra == "dev"
Requires-Dist: pytest-cov>=5.0.0; extra == "dev"
Requires-Dist: pytest-benchmark>=4.0.0; extra == "dev"
Requires-Dist: mypy>=1.11.0; extra == "dev"
Requires-Dist: types-PyYAML>=6.0.0; extra == "dev"
Requires-Dist: ruff>=0.6.0; extra == "dev"
Requires-Dist: black>=24.8.0; extra == "dev"
Requires-Dist: isort>=5.13.0; extra == "dev"
Requires-Dist: pre-commit>=3.8.0; extra == "dev"
Provides-Extra: examples
Requires-Dist: tqdm>=4.66.0; extra == "examples"
Provides-Extra: docs
Requires-Dist: mkdocs>=1.6.0; extra == "docs"
Requires-Dist: mkdocs-material>=9.5.0; extra == "docs"
Requires-Dist: mkdocstrings[python]>=0.25.0; extra == "docs"
Requires-Dist: pymdown-extensions>=10.0; extra == "docs"
Requires-Dist: mike>=2.1.0; extra == "docs"
Dynamic: license-file
